appchecker/__init__.py
appchecker/appchecker.py
appchecker-0.2.3.dist-info/licenses/LICENSE
appchecker-0.2.3.dist-info/METADATA
appchecker-0.2.3.dist-info/WHEEL
appchecker-0.2.3.dist-info/top_level.txt
appchecker-0.2.3.dist-info/RECORD
