Metadata-Version: 2.4
Name: AppChecker
Version: 0.2.3
Summary: Adds healthcheck for PythonApp
Home-page: https://github.com/so89bur/AppChecker
Author: Sov Bur
Requires-Python: >=3.8
License-File: LICENSE
Requires-Dist: halo>=0.0.31
Dynamic: author
Dynamic: home-page
Dynamic: license-file
Dynamic: requires-python
